pdf2vectors/Upload.py
pdf2vectors/__init__.py
pdf2vectors-0.1.2.dist-info/LICENSE
pdf2vectors-0.1.2.dist-info/METADATA
pdf2vectors-0.1.2.dist-info/WHEEL
pdf2vectors-0.1.2.dist-info/top_level.txt
pdf2vectors-0.1.2.dist-info/RECORD
