Metadata-Version: 2.1
Name: pdf2vectors
Version: 0.1.2
Summary: A package to interact with vectors DB
Home-page: https://github.com/ruteru/pdf2vectors
Author: Andres Garcia
Author-email: garcicon45@gmail.com
Classifier: Programming Language :: Python :: 3
Classifier: License :: OSI Approved :: MIT License
Classifier: Operating System :: OS Independent
License-File: LICENSE
Requires-Dist: pdfplumber
Requires-Dist: tensorflow
Requires-Dist: requests
Requires-Dist: pinecone-client
